cotlette/__init__.py
cotlette/middlewares.py
cotlette/responses.py
cotlette/shortcuts.py
cotlette/apps/__init__.py
cotlette/apps/config.py
cotlette/apps/registry.py
cotlette/conf/__init__.py
cotlette/conf/global_settings.py
cotlette/conf/app_template/__init__.py-tpl
cotlette/conf/app_template/admin.py-tpl
cotlette/conf/app_template/api.py-tpl
cotlette/conf/app_template/apps.py-tpl
cotlette/conf/app_template/controlles.py-tpl
cotlette/conf/app_template/models.py-tpl
cotlette/conf/app_template/tests.py-tpl
cotlette/conf/app_template/urls.py-tpl
cotlette/conf/app_template/views.py-tpl
cotlette/conf/project_template/README.md-tpl
cotlette/conf/project_template/alembic.ini-tpl
cotlette/conf/project_template/manage.py-tpl
cotlette/conf/project_template/requirements.txt-tpl
cotlette/conf/project_template/apps/__init__.py-tpl
cotlette/conf/project_template/apps/home/__init__.py-tpl
cotlette/conf/project_template/apps/home/admin.py-tpl
cotlette/conf/project_template/apps/home/api.py-tpl
cotlette/conf/project_template/apps/home/apps.py-tpl
cotlette/conf/project_template/apps/home/controlles.py-tpl
cotlette/conf/project_template/apps/home/models.py-tpl
cotlette/conf/project_template/apps/home/tests.py-tpl
cotlette/conf/project_template/apps/home/urls.py-tpl
cotlette/conf/project_template/apps/home/views.py-tpl
cotlette/conf/project_template/config/settings.py-tpl
cotlette/conf/project_template/config/urls.py-tpl
cotlette/conf/project_template/core/__init__.py-tpl
cotlette/conf/project_template/static/.gitkeep
cotlette/conf/project_template/templates/base.html-tpl
cotlette/conf/project_template/templates/home/about.html-tpl
cotlette/conf/project_template/templates/home/home.html-tpl
cotlette/conf/project_template/templates/home/private.html-tpl
cotlette/conf/project_template/utils/__init__.py-tpl
cotlette/contrib/admin/__init__.py
cotlette/contrib/admin/admin.py
cotlette/contrib/admin/apps.py
cotlette/contrib/admin/controlles.py
cotlette/contrib/admin/models.py
cotlette-0.0.30.dist-info/licenses/LICENSE
cotlette-0.0.30.dist-info/METADATA
cotlette-0.0.30.dist-info/WHEEL
cotlette-0.0.30.dist-info/entry_points.txt
cotlette-0.0.30.dist-info/top_level.txt
cotlette-0.0.30.dist-info/RECORD
