Metadata-Version: 2.4
Name: cotlette
Version: 0.0.30
Summary: FastAPI sizzles, Django dazzles. The best of both worlds in one framework.
Home-page: https://github.com/ForceFledgling/cotlette
Author: Vladimir Penzin
Author-email: Vladimir Penzin <pvenv@icloud.com>
License: MIT License
Project-URL: Homepage, https://github.com/ForceFledgling/cotlette
Project-URL: Documentation, https://github.com/ForceFledgling/cotlette
Project-URL: Source, https://github.com/ForceFledgling/cotlette
Project-URL: Tracker, https://github.com/ForceFledgling/cotlette/issues
Classifier: Development Status :: 2 - Pre-Alpha
Classifier: Environment :: Web Environment
Classifier: Framework :: FastAPI
Classifier: Intended Audience :: Developers
Classifier: License :: OSI Approved :: MIT License
Classifier: Operating System :: OS Independent
Classifier: Programming Language :: Python
Classifier: Programming Language :: Python :: 3
Classifier: Programming Language :: Python :: 3 :: Only
Classifier: Programming Language :: Python :: 3.6
Classifier: Programming Language :: Python :: 3.12
Classifier: Topic :: Internet :: WWW/HTTP
Classifier: Topic :: Internet :: WWW/HTTP :: Dynamic Content
Classifier: Topic :: Software Development :: Libraries :: Application Frameworks
Classifier: Topic :: Software Development :: Libraries :: Python Modules
Requires-Python: >=3.6
License-File: LICENSE
Requires-Dist: uvicorn<0.20.0
Requires-Dist: fastapi<0.100.0
Requires-Dist: asgiref<4.0.0
Requires-Dist: jinja2<3.2.0
Requires-Dist: bcrypt<4.1.0
Requires-Dist: pyjwt<2.8.0
Requires-Dist: itsdangerous<2.2.0
Requires-Dist: python-multipart<0.1.0
Requires-Dist: sqlalchemy<2.0.0
Requires-Dist: alembic<1.12.0
Requires-Dist: click<8.2.0
Dynamic: author
Dynamic: home-page
Dynamic: license-file
Dynamic: requires-python
